yoloxyz/__init__.py
yoloxyz-0.0.dist-info/LICENSE
yoloxyz-0.0.dist-info/METADATA
yoloxyz-0.0.dist-info/WHEEL
yoloxyz-0.0.dist-info/top_level.txt
yoloxyz-0.0.dist-info/zip-safe
yoloxyz-0.0.dist-info/RECORD
